wavekit/__init__.py
wavekit/fsdb_reader.py
wavekit/npi_fsdb.pxd
wavekit/npi_fsdb_reader.pyx
wavekit/pattern_parser.py
wavekit/reader.py
wavekit/value_change.cpython-310-x86_64-linux-gnu.so
wavekit/value_change.pyx
wavekit/vcd_reader.py
wavekit/waveform.py
wavekit-0.1.2.dist-info/LICENSE
wavekit-0.1.2.dist-info/METADATA
wavekit-0.1.2.dist-info/WHEEL
wavekit-0.1.2.dist-info/RECORD
