Metadata-Version: 2.1
Name: wavekit
Version: 0.1.2
Summary: a fundamental package for digital circuit waveform analysis
Home-page: https://github.com/cxzzzz/wavekit
Author: cxzzzz
Author-email: cxz19961010@outlook.com
Requires-Python: >=3.9,<4.0
Classifier: Programming Language :: Python :: 3
Classifier: Programming Language :: Python :: 3.9
Classifier: Programming Language :: Python :: 3.10
Classifier: Programming Language :: Python :: 3.11
Classifier: Programming Language :: Python :: 3.12
Classifier: Programming Language :: Python :: 3.13
Requires-Dist: numpy (>=2.0.0,<3.0.0)
Requires-Dist: pytest (>=8.2.2,<9.0.0)
Requires-Dist: vcdvcd (>=2.3.5,<3.0.0)
Project-URL: Repository, https://github.com/cxzzzz/wavekit
